stackone/__init__.py
stackone/client.py
stackone/core/__init__.py
stackone/core/api_error.py
stackone/core/client_wrapper.py
stackone/core/datetime_utils.py
stackone/core/jsonable_encoder.py
stackone/core/remove_none_from_dict.py
stackone/environment.py
stackone/py.typed
stackone/resources/__init__.py
stackone/resources/ats/__init__.py
stackone/resources/ats/client.py
stackone/resources/ats/errors/__init__.py
stackone/resources/ats/errors/bad_request_error.py
stackone/resources/ats/errors/forbidden_error.py
stackone/resources/ats/errors/internal_server_error.py
stackone/resources/ats/errors/not_found_error.py
stackone/resources/ats/errors/not_implemented_error.py
stackone/resources/ats/errors/too_many_requests_error.py
stackone/resources/ats/resources/__init__.py
stackone/resources/ats/resources/accounts/__init__.py
stackone/resources/ats/resources/accounts/client.py
stackone/resources/ats/resources/applications/__init__.py
stackone/resources/ats/resources/applications/client.py
stackone/resources/ats/resources/candidates/__init__.py
stackone/resources/ats/resources/candidates/client.py
stackone/resources/ats/resources/connect_sessions/__init__.py
stackone/resources/ats/resources/connect_sessions/client.py
stackone/resources/ats/resources/departments/__init__.py
stackone/resources/ats/resources/departments/client.py
stackone/resources/ats/resources/interview_stages/__init__.py
stackone/resources/ats/resources/interview_stages/client.py
stackone/resources/ats/resources/interviews/__init__.py
stackone/resources/ats/resources/interviews/client.py
stackone/resources/ats/resources/job_postings/__init__.py
stackone/resources/ats/resources/job_postings/client.py
stackone/resources/ats/resources/jobs/__init__.py
stackone/resources/ats/resources/jobs/client.py
stackone/resources/ats/resources/locations/__init__.py
stackone/resources/ats/resources/locations/client.py
stackone/resources/ats/resources/rejected_reasons/__init__.py
stackone-0.0.16.dist-info/METADATA
stackone-0.0.16.dist-info/WHEEL
stackone-0.0.16.dist-info/RECORD
